<?xml version='1.0' encoding='utf-8'?>
<root>
  <row>
    <PGC>2</PGC>
    <OBJNAME>UGC12889</OBJNAME>
    <ID_NED>UGC 12889</ID_NED>
    <ID_NEDD>UGC 12889</ID_NEDD>
    <ID_2MASS>00000168+4716282</ID_2MASS>
    <SDSS_PHOTID>-</SDSS_PHOTID>
    <SDSS_SPECID>-</SDSS_SPECID>
    <RA>0.006945</RA>
    <DEC>47.274581</DEC>
    <F_ASTROM>0</F_ASTROM>
    <R1>0.933</R1>
    <R2>0.589</R2>
    <PA>163.5</PA>
    <RSOURCE>H</RSOURCE>
    <RFLAG>1</RFLAG>
    <T>3.1</T>
    <E_T>0.4</E_T>
    <INCL>53.37</INCL>
    <V>5016.7</V>
    <E_V>6.4</E_V>
    <V_VIR>5203.2</V_VIR>
    <E_V_VIR>10.43</E_V_VIR>
    <NDIST>1</NDIST>
    <EDIST>1</EDIST>
    <D>67.9204</D>
    <E_D>12.5114</E_D>
    <D_LO68>56.4937</D_LO68>
    <D_HI68>81.6582</D_HI68>
    <D_LO95>46.9894</D_LO95>
    <D_HI95>98.1748</D_HI95>
    <DMETHOD>N</DMETHOD>
    <BT>14.241</BT>
    <E_BT>0.605</E_BT>
    <AG>0.526</AG>
    <AI>0.296</AI>
    <Q12>0</Q12>
    <Q25>0</Q25>
    <Q60>0</Q60>
    <Q100>0</Q100>
    <WFPOINT>0</WFPOINT>
    <WFTREAT>0</WFTREAT>
    <J>10.643</J>
    <H>9.892</H>
    <K>9.542</K>
    <E_J>0.03</E_J>
    <E_H>0.031</E_H>
    <E_K>0.039</E_K>
    <FLAG_2MASS>2</FLAG_2MASS>
    <logL_K>11.1632</logL_K>
    <logM_HEC>11.078</logM_HEC>
    <FLAG_METAL>-1</FLAG_METAL>
    <CLASS_SP>-1</CLASS_SP>
    <AGN_S17>?</AGN_S17>
    <AGN_HEC>?</AGN_HEC>
  </row>
  <row>
    <PGC>3</PGC>
    <OBJNAME>PGC000003</OBJNAME>
    <ID_NED>MCG -03-01-012</ID_NED>
    <ID_IRAS>F23574-1817</ID_IRAS>
    <ID_2MASS>00000316-1800289</ID_2MASS>
    <SDSS_PHOTID>-</SDSS_PHOTID>
    <SDSS_SPECID>-</SDSS_SPECID>
    <RA>0.013125</RA>
    <DEC>-18.0082</DEC>
    <F_ASTROM>1</F_ASTROM>
    <R1>0.33</R1>
    <R2>0.33</R2>
    <PA>0.0</PA>
    <RSOURCE>H</RSOURCE>
    <RFLAG>2</RFLAG>
    <T>4.9</T>
    <E_T>2.3</E_T>
    <INCL>67.08</INCL>
    <V>8954.0</V>
    <E_V>29.0</E_V>
    <V_VIR>8843.6</V_VIR>
    <E_V_VIR>32.26</E_V_VIR>
    <NDIST>0</NDIST>
    <EDIST>0</EDIST>
    <D>124.2548</D>
    <E_D>15.7349</E_D>
    <D_LO68>109.4754</D_LO68>
    <D_HI68>141.0294</D_HI68>
    <D_LO95>96.454</D_LO95>
    <D_HI95>160.0687</D_HI95>
    <DMETHOD>Z</DMETHOD>
    <BT>15.15</BT>
    <E_BT>0.5</E_BT>
    <AG>0.105</AG>
    <AI>0.61</AI>
    <S12>0.3972</S12>
    <S25>0.1855</S25>
    <S60>0.264</S60>
    <S100>0.7494</S100>
    <Q12>1</Q12>
    <Q25>1</Q25>
    <Q60>3</Q60>
    <Q100>1</Q100>
    <WFPOINT>0</WFPOINT>
    <WFTREAT>0</WFTREAT>
    <J>15.466</J>
    <H>14.946</H>
    <K>14.645</K>
    <E_J>0.103</E_J>
    <E_H>0.14</E_H>
    <E_K>0.133</E_K>
    <FLAG_2MASS>3</FLAG_2MASS>
    <logL_60u>43.3868</logL_60u>
    <logL_K>9.6466</logL_K>
    <logSFR_60u>0.322</logSFR_60u>
    <logSFR_HEC>0.425</logSFR_HEC>
    <FLAG_SFR_HEC>F3</FLAG_SFR_HEC>
    <logM_HEC>9.5614</logM_HEC>
    <FLAG_METAL>-1</FLAG_METAL>
    <CLASS_SP>-1</CLASS_SP>
    <AGN_S17>?</AGN_S17>
    <AGN_HEC>?</AGN_HEC>
  </row>
  <row>
    <PGC>4</PGC>
    <OBJNAME>PGC000004</OBJNAME>
    <ID_NED>KUG 2357+228</ID_NED>
    <ID_NEDD>KUG 2357+228</ID_NEDD>
    <SDSS_PHOTID>1237679478544072744</SDSS_PHOTID>
    <SDSS_SPECID>-</SDSS_SPECID>
    <RA>0.014292</RA>
    <DEC>23.087596</DEC>
    <F_ASTROM>1</F_ASTROM>
    <R1>0.428</R1>
    <R2>0.095</R2>
    <PA>63.2</PA>
    <RSOURCE>H</RSOURCE>
    <RFLAG>1</RFLAG>
    <T>5.0</T>
    <E_T>1.2</E_T>
    <INCL>84.68</INCL>
    <V>4461.7</V>
    <E_V>3.7</E_V>
    <V_VIR>4546.9</V_VIR>
    <E_V_VIR>11.92</E_V_VIR>
    <NDIST>2</NDIST>
    <EDIST>1</EDIST>
    <D>53.9879</D>
    <E_D>8.501</E_D>
    <D_LO68>46.9063</D_LO68>
    <D_HI68>63.152</D_HI68>
    <D_LO95>42.5164</D_LO95>
    <D_HI95>80.0394</D_HI95>
    <DMETHOD>N</DMETHOD>
    <BT>16.88</BT>
    <E_BT>0.433</E_BT>
    <AG>0.395</AG>
    <AI>1.068</AI>
    <Q12>0</Q12>
    <Q25>0</Q25>
    <Q60>0</Q60>
    <Q100>0</Q100>
    <WF1>13.256657</WF1>
    <WF2>13.285035</WF2>
    <WF3>11.664301</WF3>
    <WF4>11.276231</WF4>
    <E_WF1>0.00742</E_WF1>
    <E_WF2>0.025905</E_WF2>
    <E_WF3>0.324935</E_WF3>
    <E_WF4>4.781138</E_WF4>
    <WFPOINT>0</WFPOINT>
    <WFTREAT>0</WFTREAT>
    <FLAG_2MASS>0</FLAG_2MASS>
    <U>17.861</U>
    <G>16.388</G>
    <R>15.87</R>
    <I>15.619</I>
    <Z>15.433</Z>
    <E_U>0.036</E_U>
    <E_G>0.006</E_G>
    <E_R>0.005</E_R>
    <E_I>0.007</E_I>
    <E_Z>0.016</E_Z>
    <ML_RATIO>0.782</ML_RATIO>
    <FLAG_METAL>-1</FLAG_METAL>
    <CLASS_SP>-1</CLASS_SP>
    <AGN_S17>?</AGN_S17>
    <AGN_HEC>?</AGN_HEC>
  </row>
  <row>
    <PGC>5</PGC>
    <OBJNAME>IC5370</OBJNAME>
    <ID_NED>IC 5370</ID_NED>
    <ID_2MASS>00000914+3244182</ID_2MASS>
    <SDSS_PHOTID>1237663234987458745</SDSS_PHOTID>
    <SDSS_SPECID>-</SDSS_SPECID>
    <RA>0.038121</RA>
    <DEC>32.73842</DEC>
    <F_ASTROM>0</F_ASTROM>
    <R1>0.391</R1>
    <R2>0.391</R2>
    <PA>0.0</PA>
    <RSOURCE>H</RSOURCE>
    <RFLAG>2</RFLAG>
    <T>-0.6</T>
    <E_T>1.2</E_T>
    <INCL>26.59</INCL>
    <V>10365.2</V>
    <E_V>16.0</E_V>
    <V_VIR>10493.7</V_VIR>
    <E_V_VIR>18.93</E_V_VIR>
    <NDIST>0</NDIST>
    <EDIST>0</EDIST>
    <D>146.2144</D>
    <E_D>16.7162</E_D>
    <D_LO68>130.4184</D_LO68>
    <D_HI68>163.9236</D_HI68>
    <D_LO95>116.3289</D_LO95>
    <D_HI95>183.7777</D_HI95>
    <DMETHOD>Z</DMETHOD>
    <BT>14.759</BT>
    <E_BT>0.334</E_BT>
    <AG>0.212</AG>
    <AI>0.0</AI>
    <Q12>0</Q12>
    <Q25>0</Q25>
    <Q60>0</Q60>
    <Q100>0</Q100>
    <WF1>10.308943</WF1>
    <WF2>10.292552</WF2>
    <WF3>9.330194</WF3>
    <WF4>8.24662</WF4>
    <E_WF1>0.000366</E_WF1>
    <E_WF2>0.001237</E_WF2>
    <E_WF3>0.029803</E_WF3>
    <E_WF4>0.249182</E_WF4>
    <WFPOINT>0</WFPOINT>
    <WFTREAT>0</WFTREAT>
    <J>11.546</J>
    <H>10.837</H>
    <K>10.511</K>
    <E_J>0.021</E_J>
    <E_H>0.024</E_H>
    <E_K>0.033</E_K>
    <FLAG_2MASS>2</FLAG_2MASS>
    <U>16.127</U>
    <G>14.276</G>
    <R>13.45</R>
    <I>13.08</I>
    <Z>12.793</Z>
    <E_U>0.007</E_U>
    <E_G>0.002</E_G>
    <E_R>0.002</E_R>
    <E_I>0.002</E_I>
    <E_Z>0.002</E_Z>
    <logL_12u>42.5742</logL_12u>
    <logL_22u>42.1202</logL_22u>
    <logL_K>11.4416</logL_K>
    <ML_RATIO>0.899</ML_RATIO>
    <logSFR_12u>0.233</logSFR_12u>
    <logSFR_22u>-0.198</logSFR_22u>
    <logSFR_HEC>0.222</logSFR_HEC>
    <FLAG_SFR_HEC>W3</FLAG_SFR_HEC>
    <logM_HEC>11.3953</logM_HEC>
    <FLAG_METAL>-1</FLAG_METAL>
    <CLASS_SP>-1</CLASS_SP>
    <AGN_S17>?</AGN_S17>
    <AGN_HEC>?</AGN_HEC>
  </row>
  <row>
    <PGC>6</PGC>
    <OBJNAME>PGC000006</OBJNAME>
    <ID_NED>KUG 2357+156</ID_NED>
    <ID_IRAS>F23574+1535</ID_IRAS>
    <ID_2MASS>00000214+1552539</ID_2MASS>
    <SDSS_PHOTID>1237656496724312079</SDSS_PHOTID>
    <SDSS_SPECID>844551136588359680</SDSS_SPECID>
    <RA>0.008763</RA>
    <DEC>15.88167</DEC>
    <F_ASTROM>0</F_ASTROM>
    <R1>0.2</R1>
    <R2>0.144</R2>
    <PA>89.6</PA>
    <RSOURCE>H</RSOURCE>
    <RFLAG>1</RFLAG>
    <T>3.5</T>
    <E_T>4.7</E_T>
    <INCL>45.67</INCL>
    <V>6003.3</V>
    <E_V>2.6</E_V>
    <V_VIR>6054.5</V_VIR>
    <E_V_VIR>12.42</E_V_VIR>
    <NDIST>0</NDIST>
    <EDIST>0</EDIST>
    <D>85.6908</D>
    <E_D>12.9795</E_D>
    <D_LO68>73.6465</D_LO68>
    <D_HI68>99.7048</D_HI68>
    <D_LO95>63.2951</D_LO95>
    <D_HI95>116.0107</D_HI95>
    <DMETHOD>Z</DMETHOD>
    <UT>16.575</UT>
    <BT>15.546</BT>
    <E_UT>0.016</E_UT>
    <E_BT>0.346</E_BT>
    <AG>0.214</AG>
    <AI>0.223</AI>
    <S12>0.1322</S12>
    <S25>0.0949</S25>
    <S60>0.3516</S60>
    <S100>1.029</S100>
    <Q12>1</Q12>
    <Q25>1</Q25>
    <Q60>3</Q60>
    <Q100>2</Q100>
    <WF1>12.10069</WF1>
    <WF2>12.002372</WF2>
    <WF3>8.327887</WF3>
    <WF4>7.335429</WF4>
    <E_WF1>0.001817</E_WF1>
    <E_WF2>0.00575</E_WF2>
    <E_WF3>0.011515</E_WF3>
    <E_WF4>0.10074</E_WF4>
    <WFPOINT>0</WFPOINT>
    <WFTREAT>0</WFTREAT>
    <J>13.206</J>
    <H>12.541</H>
    <K>12.231</K>
    <E_J>0.049</E_J>
    <E_H>0.072</E_H>
    <E_K>0.079</E_K>
    <FLAG_2MASS>2</FLAG_2MASS>
    <U>16.58</U>
    <G>15.462</G>
    <R>14.909</R>
    <I>14.632</I>
    <Z>14.374</Z>
    <E_U>0.013</E_U>
    <E_G>0.003</E_G>
    <E_R>0.003</E_R>
    <E_I>0.003</E_I>
    <E_Z>0.005</E_Z>
    <logL_60u>43.1885</logL_60u>
    <logL_12u>42.511</logL_12u>
    <logL_22u>42.0206</logL_22u>
    <logL_K>10.2895</logL_K>
    <ML_RATIO>0.794</ML_RATIO>
    <logSFR_60u>0.124</logSFR_60u>
    <logSFR_12u>0.177</logSFR_12u>
    <logSFR_22u>-0.289</logSFR_22u>
    <logSFR_HEC>0.227</logSFR_HEC>
    <FLAG_SFR_HEC>F3</FLAG_SFR_HEC>
    <logM_HEC>10.1894</logM_HEC>
    <logSFR_GSW>-0.239</logSFR_GSW>
    <logM_GSW>9.94</logM_GSW>
    <MIN_SNR>21.2</MIN_SNR>
    <METAL>8.7275</METAL>
    <FLAG_METAL>0</FLAG_METAL>
    <CLASS_SP>0</CLASS_SP>
    <AGN_S17>?</AGN_S17>
    <AGN_HEC>N</AGN_HEC>
  </row>
  <row>
    <PGC>7</PGC>
    <OBJNAME>PGC000007</OBJNAME>
    <ID_NED>ARK 590</ID_NED>
    <ID_NEDD>ARK 590</ID_NEDD>
    <ID_2MASS>00000442-0004599</ID_2MASS>
    <SDSS_PHOTID>1237657190905217071</SDSS_PHOTID>
    <SDSS_SPECID>1228395055081875456</SDSS_SPECID>
    <RA>0.018555</RA>
    <DEC>-0.083357</DEC>
    <F_ASTROM>0</F_ASTROM>
    <R1>0.287</R1>
    <R2>0.232</R2>
    <PA>161.1</PA>
    <RSOURCE>H</RSOURCE>
    <RFLAG>1</RFLAG>
    <T>-3.2</T>
    <E_T>2.2</E_T>
    <INCL>44.77</INCL>
    <V>7125.0</V>
    <E_V>2.6</E_V>
    <V_VIR>7098.8</V_VIR>
    <E_V_VIR>13.76</E_V_VIR>
    <NDIST>1</NDIST>
    <EDIST>1</EDIST>
    <D>95.9401</D>
    <E_D>20.3237</E_D>
    <D_LO68>77.6247</D_LO68>
    <D_HI68>118.577</D_HI68>
    <D_LO95>62.8058</D_LO95>
    <D_HI95>146.555</D_HI95>
    <DMETHOD>N</DMETHOD>
    <UT>17.007</UT>
    <BT>15.626</BT>
    <E_UT>0.073</E_UT>
    <E_BT>0.316</E_BT>
    <AG>0.145</AG>
    <AI>0.0</AI>
    <Q12>0</Q12>
    <Q25>0</Q25>
    <Q60>0</Q60>
    <Q100>0</Q100>
    <WF1>11.545856</WF1>
    <WF2>11.537526</WF2>
    <WF3>11.033997</WF3>
    <E_WF1>0.001461</E_WF1>
    <E_WF2>0.005139</E_WF2>
    <E_WF3>0.194006</E_WF3>
    <WFPOINT>0</WFPOINT>
    <WFTREAT>0</WFTREAT>
    <J>12.844</J>
    <H>12.2</H>
    <K>11.721</K>
    <E_J>0.055</E_J>
    <E_H>0.075</E_H>
    <E_K>0.088</E_K>
    <FLAG_2MASS>2</FLAG_2MASS>
    <U>17.119</U>
    <G>15.293</G>
    <R>14.506</R>
    <I>14.144</I>
    <Z>13.827</Z>
    <E_U>0.015</E_U>
    <E_G>0.003</E_G>
    <E_R>0.002</E_R>
    <E_I>0.002</E_I>
    <E_Z>0.004</E_Z>
    <logL_12u>41.5267</logL_12u>
    <logL_K>10.5916</logL_K>
    <ML_RATIO>0.883</ML_RATIO>
    <logSFR_12u>-0.698</logSFR_12u>
    <logSFR_HEC>-0.71</logSFR_HEC>
    <FLAG_SFR_HEC>W3</FLAG_SFR_HEC>
    <logM_HEC>10.5376</logM_HEC>
    <logSFR_GSW>-1.811</logSFR_GSW>
    <logM_GSW>10.442</logM_GSW>
    <MIN_SNR>2.06</MIN_SNR>
    <METAL>8.5968</METAL>
    <FLAG_METAL>0</FLAG_METAL>
    <CLASS_SP>2</CLASS_SP>
    <AGN_S17>?</AGN_S17>
    <AGN_HEC>Y</AGN_HEC>
  </row>
  <row>
    <PGC>10</PGC>
    <OBJNAME>PGC000010</OBJNAME>
    <ID_NED>ARK 591</ID_NED>
    <ID_2MASS>00000784-0002264</ID_2MASS>
    <SDSS_PHOTID>1237657190905217208</SDSS_PHOTID>
    <SDSS_SPECID>435776070554249216</SDSS_SPECID>
    <RA>0.032608</RA>
    <DEC>-0.040549</DEC>
    <F_ASTROM>0</F_ASTROM>
    <R1>0.279</R1>
    <R2>0.22</R2>
    <PA>131.4</PA>
    <RSOURCE>H</RSOURCE>
    <RFLAG>1</RFLAG>
    <T>-0.9</T>
    <E_T>2.6</E_T>
    <INCL>42.67</INCL>
    <V>7092.9</V>
    <E_V>2.7</E_V>
    <V_VIR>7066.9</V_VIR>
    <E_V_VIR>13.77</E_V_VIR>
    <NDIST>0</NDIST>
    <EDIST>0</EDIST>
    <D>102.2506</D>
    <E_D>12.7674</E_D>
    <D_LO68>90.2481</D_LO68>
    <D_HI68>115.8492</D_HI68>
    <D_LO95>79.6546</D_LO95>
    <D_HI95>131.2564</D_HI95>
    <DMETHOD>Z</DMETHOD>
    <UT>16.749</UT>
    <BT>15.741</BT>
    <E_UT>0.13</E_UT>
    <E_BT>0.278</E_BT>
    <AG>0.143</AG>
    <AI>0.0</AI>
    <Q12>0</Q12>
    <Q25>0</Q25>
    <Q60>0</Q60>
    <Q100>0</Q100>
    <WF1>12.226629</WF1>
    <WF2>12.185693</WF2>
    <WF3>8.825584</WF3>
    <WF4>7.808808</WF4>
    <E_WF1>0.002311</E_WF1>
    <E_WF2>0.00779</E_WF2>
    <E_WF3>0.020259</E_WF3>
    <E_WF4>0.176092</E_WF4>
    <WFPOINT>0</WFPOINT>
    <WFTREAT>0</WFTREAT>
    <J>13.567</J>
    <H>12.866</H>
    <K>12.304</K>
    <E_J>0.101</E_J>
    <E_H>0.116</E_H>
    <E_K>0.118</E_K>
    <FLAG_2MASS>2</FLAG_2MASS>
    <U>16.886</U>
    <G>15.687</G>
    <R>15.124</R>
    <I>14.87</I>
    <Z>14.605</Z>
    <E_U>0.02</E_U>
    <E_G>0.003</E_G>
    <E_R>0.003</E_R>
    <E_I>0.003</E_I>
    <E_Z>0.006</E_Z>
    <logL_12u>42.4654</logL_12u>
    <logL_22u>41.9847</logL_22u>
    <logL_K>10.4137</logL_K>
    <ML_RATIO>0.798</ML_RATIO>
    <logSFR_12u>0.137</logSFR_12u>
    <logSFR_22u>-0.322</logSFR_22u>
    <logSFR_HEC>0.125</logSFR_HEC>
    <FLAG_SFR_HEC>W3</FLAG_SFR_HEC>
    <logM_HEC>10.3156</logM_HEC>
    <logSFR_GSW>-0.183</logSFR_GSW>
    <logM_GSW>10.007</logM_GSW>
    <MIN_SNR>12.1</MIN_SNR>
    <METAL>8.6701</METAL>
    <FLAG_METAL>0</FLAG_METAL>
    <CLASS_SP>0</CLASS_SP>
    <AGN_S17>?</AGN_S17>
    <AGN_HEC>N</AGN_HEC>
</row>
</root>
